Workbook

Sheet Cover Page
A49: Financial Data Presented in USD Millions

Sheet Historical Data 
A1: Historical Data Between 2023 and 2025
A3: Item | B3: FY23A | C3: FY24A | D3: FY25A
A4: Revenue | B4: 383285 | C4: 391035 | D4: 416161
A5: EBIT | B5: 114301 | C5: 123216 | D5: 133050
A6: EBIT Margin | B6: =B5/B4 -> 0.29821412 | C6: =C5/C4 -> 0.31510223 | D6: =D5/D4 -> 0.319708
A7: Net Income | B7: 96995 | C7: 93736 | D7: 112010
A8: D&A | B8: 11519 | C8: 11445 | D8: 11698
A9: Operating Cash Flow | B9: 110543 | C9: 118254 | D9: 111482
A10: Capex | B10: 10959 | C10: 9447 | D10: 12715
A11: Capex % Revenue | B11: =B10/B4 -> 0.028592301 | C11: =C10/C4 -> 0.024158963 | D11: =D10/D4 -> 0.030553079
A12: Cash | B12: 29965 | C12: 29943 | D12: 35934
A13: Short Term Debt | B13: =9822+5985 -> 15807 | C13: =10912+9967 -> 20879 | D13: =12350+7979 -> 20329
A14: Long Term Debt | B14: =95281 -> 95281 | C14: 85750 | D14: 78328
A15: Total Debt | B15: =B13+B14 -> 111088 | C15: =C13+C14 -> 106629 | D15: =D13+D14 -> 98657
A16: Net Debt | B16: =B15-B12 -> 81123 | C16: =C15-C12 -> 76686 | D16: =D15-D12 -> 62723

Sheet Forecast 
A1: Item | B1: FY23A | C1: FY24A | D1: FY25A | E1: FY26E | F1: FY27E | G1: FY28E | H1: FY29E | I1: FY30E
A2: Revenue | B2: ='Historical Data '!B4 -> 383285 | C2: ='Historical Data '!C4 -> 391035 | D2: ='Historical Data '!D4 -> 416161 | E2: =D2*(1+E3) -> 436969.05 | F2: =E2*(1+F3) -> 456632.66 | G2: =F2*(1+G3) -> 474897.96 | H2: =G2*(1+H3) -> 491519.39 | I2: =H2*(1+I3) -> 506264.97
A3: Revenue Growth | C3: =C2/B2-1 -> 0.020219941 | D3: =D2/C2-1 -> 0.064255118 | E3: 0.05 | F3: 0.045 | G3: 0.04 | H3: 0.035 | I3: 0.03
A4: EBIT Margin | B4: ='Historical Data '!B6 -> 0.29821412 | C4: ='Historical Data '!C6 -> 0.31510223 | D4: ='Historical Data '!D6 -> 0.319708 | E4: =D4 -> 0.319708 | F4: =E4 -> 0.319708 | G4: =F4 -> 0.319708 | H4: =G4 -> 0.319708 | I4: =H4 -> 0.319708
A5: EBIT | B5: =Table1[[#This Row],[FY23A]] -> 114301 | C5: =Table1[[#This Row],[FY24A]] -> 123216 | D5: =Table1[[#This Row],[FY25A]] -> 133050 | E5: =E2*E4 -> 139702.5 | F5: =F2*F4 -> 145989.11 | G5: =G2*G4 -> 151828.68 | H5: =H2*H4 -> 157142.68 | I5: =I2*I4 -> 161856.96
A6: Tax Rate | B6: =16741/113736 -> 0.14719174 | C6: =29749/123485 -> 0.24091185 | D6: =20719/132729 -> 0.15610002 | E6: 0.16 | F6: 0.16 | G6: 0.16 | H6: 0.16 | I6: 0.16
A7: NOPAT | B7: =B5*(1-B6) -> 97476.837 | C7: =C5*(1-C6) -> 93531.805 | D7: =D5*(1-D6) -> 112280.89 | E7: =E5*(1-E6) -> 117350.1 | F7: =F5*(1-F6) -> 122630.85 | G7: =G5*(1-G6) -> 127536.09 | H7: =H5*(1-H6) -> 131999.85 | I7: =I5*(1-I6) -> 135959.85
A8: D&A % Revenue | B8: =B9/B2 -> 0.030053355 | C8: =C9/C2 -> 0.02926848 | D8: =D9/D2 -> 0.028109313 | E8: =D8 -> 0.028109313 | F8: =E8 -> 0.028109313 | G8: =F8 -> 0.028109313 | H8: =G8 -> 0.028109313 | I8: =H8 -> 0.028109313
A9: D&A | B9: ='Historical Data '!B8 -> 11519 | C9: ='Historical Data '!C8 -> 11445 | D9: ='Historical Data '!D8 -> 11698 | E9: =E2*E8 -> 12282.9 | F9: =F2*F8 -> 12835.63 | G9: =G2*G8 -> 13349.056 | H9: =H2*H8 -> 13816.273 | I9: =I2*I8 -> 14230.761
A10: Capex % Revenue | B10: =B11/B2 -> 0.028592301 | C10: =C11/C2 -> 0.024158963 | D10: =D11/D2 -> 0.030553079 | E10: =D10 -> 0.030553079 | F10: =E10 -> 0.030553079 | G10: =F10 -> 0.030553079 | H10: =G10 -> 0.030553079 | I10: =H10 -> 0.030553079
A11: Capex | B11: ='Historical Data '!B10 -> 10959 | C11: ='Historical Data '!C10 -> 9447 | D11: ='Historical Data '!D10 -> 12715 | E11: =E2*E10 -> 13350.75 | F11: =F2*F10 -> 13951.534 | G11: =G2*G10 -> 14509.595 | H11: =H2*H10 -> 15017.431 | I11: =I2*I10 -> 15467.954
A12: FCF | E12: =E7+E9-E11 -> 116282.25 | F12: =F7+F9-F11 -> 121514.95 | G12: =G7+G9-G11 -> 126375.55 | H12: =H7+H9-H11 -> 130798.69 | I12: =I7+I9-I11 -> 134722.65
A19: Assumption
A20: 1. Revenue Growth Assumptio
A21: Year | B21: Assumption
A22: FY26E | B22: 0.05
A23: FY27E | B23: 0.045
A24: FY28E | B24: 0.04
A25: FY29E | B25: 0.035
A26: FY30E | B26: 0.03
A28: 2. EBIT Margin Assumption
A29: Year | B29: EBIT Margin
A30: FY26E-FY30E | B30: 0.32
A32: 3. Tax Rate Assumption
A33: Year | B33: Tax Rate
A34: FY26E-FY30E | B34: 0.16
A36: 4. D&A Assumption
A37: Year | B37: D&A % Revenue
A38: FY26E-FY30E | B38: 0.028
A40: 5.Capex Assumption
A41: Year | B41: Capex % Revenue
A42: FY26E-FY30E | B42: 0.031

Sheet DCF & Sensitivity Analysis
A1: Assumption | B1: Value | R1: Sensitivity Analysis
A2: WACC | B2: 0.08
A3: Terminal Growth | B3: 0.025
A5: Condition | B5: Value
A6: Diluted Shares Outstanding | B6: 15004697
A7: Current Price | B7: 315.32
A8: Net Debt | B8: ='Historical Data '!D16 -> 62723 | O8: ENTERPRISE VALUE | X8: EQUITY VALUE PER SHARE
A9: Item | B9: FY26E | C9: FY27E | D9: FY28E | E9: FY29E | F9: FY30E | G9: FY31E
A10: FCF | B10: ='Forecast '!E12 -> 116282.25 | C10: ='Forecast '!F12 -> 121514.95 | D10: ='Forecast '!G12 -> 126375.55 | E10: ='Forecast '!H12 -> 130798.69 | F10: ='Forecast '!I12 -> 134722.65 | G10: =Table3[[#This Row],[FY30E]]*(1+B3) -> 138090.72
A11: Discount Factor | B11: =1/(1+$B$2)^1 -> 0.92592593 | C11: =1/(1+$B$2)^2 -> 0.85733882 | D11: =1/(1+$B$2)^3 -> 0.79383224 | E11: =1/(1+$B$2)^4 -> 0.73502985 | F11: =1/(1+$B$2)^5 -> 0.6805832 | O11: Terminal Growth Rate | Y11: Terminal Growth Rate
A12: PV of Discrete | B12: =B10*B11 -> 107668.75 | C12: =C10*C11 -> 104179.48 | D12: =D10*D11 -> 100320.99 | E12: =E10*E11 -> 96140.944 | F12: =F10*F11 -> 91689.975 | L12: =C36 -> 2208767.9 | M12: 0.015 | N12: 0.02 | O12: 0.025 | P12: 0.03 | Q12: 0.035 | W12: 0.015 | X12: 0.02 | Y12: 0.025 | Z12: 0.03 | AA12: 0.035
A13: Terminal Value | F13: =G10/(B2-B3) -> 2510740.4 | L13: 0.06 | M13: 2798959.4 | N13: 3095384.3 | O13: 3476502 | P13: 3984659 | Q13: 4696078.7 | V13: 0.06 | W13: =M26/$B$6*1000 -> 182.35866 | X13: =N26/$B$6*1000 -> 202.11413 | Y13: =O26/$B$6*1000 -> 227.51403 | Z13: =P26/$B$6*1000 -> 261.38055 | AA13: =Q26/$B$6*1000 -> 308.79369
A14: PV of Terminal | F14: =F13/(1+B2)^5 -> 1708767.7 | L14: 0.07 | M14: 2286470.6 | N14: 2473342 | O14: 2701740.4 | P14: 2987238.4 | Q14: 3354307.2 | V14: 0.07 | W14: =M27/$B$6*1000 -> 148.20343 | X14: =N27/$B$6*1000 -> 160.65763 | Y14: =O27/$B$6*1000 -> 175.87942 | Z14: =P27/$B$6*1000 -> 194.90666 | AA14: =Q27/$B$6*1000 -> 219.37025
A15: Total Cash Flow | B15: =B12+B14 -> 107668.75 | C15: =C12+C14 -> 104179.48 | D15: =D12+D14 -> 100320.99 | E15: =E12+E14 -> 96140.944 | F15: =F12+F14 -> 1800457.7 | K15: WA | L15: 0.08 | M15: 1931774.4 | N15: 2058729.7 | O15: 2208767.9 | P15: 2388813.6 | Q15: 2608869.6 | U15: WA | V15: 0.08 | W15: =M28/$B$6*1000 -> 124.56442 | X15: =N28/$B$6*1000 -> 133.02546 | Y15: =O28/$B$6*1000 -> 143.02487 | Z15: =P28/$B$6*1000 -> 155.02416 | AA15: =Q28/$B$6*1000 -> 169.68997
K16: CC | L16: 0.09 | M16: 1671749.5 | N16: 1762645.7 | O16: 1867525.8 | P16: 1989886 | Q16: 2134493.4 | U16: CC | V16: 0.09 | W16: =M29/$B$6*1000 -> 107.23486 | X16: =N29/$B$6*1000 -> 113.2927 | Y16: =O29/$B$6*1000 -> 120.28252 | Z16: =P29/$B$6*1000 -> 128.43731 | AA16: =Q29/$B$6*1000 -> 138.07479
L17: 0.1 | M17: 1472979.3 | N17: 1540639.1 | O17: 1617320.3 | P17: 1704955.9 | Q17: 1806073.9 | V17: 0.1 | W17: =M30/$B$6*1000 -> 93.987655 | X17: =N30/$B$6*1000 -> 98.496899 | Y17: =O30/$B$6*1000 -> 103.60738 | Z17: =P30/$B$6*1000 -> 109.44792 | AA17: =Q30/$B$6*1000 -> 116.18701
O21: EQUITY VALUE | W21: PREMIUM(DISCOUNT) TO CURRENT PRICE
O24: Terminal Growth Rate | Y24: Terminal Growth Rate
M25: 0.015 | N25: 0.02 | O25: 0.025 | P25: 0.03 | Q25: 0.035 | W25: 0.015 | X25: 0.02 | Y25: 0.025 | Z25: 0.03 | AA25: 0.035
L26: 0.06 | M26: =M13-$B$8 -> 2736236.4 | N26: =N13-$B$8 -> 3032661.3 | O26: =O13-$B$8 -> 3413779 | P26: =P13-$B$8 -> 3921936 | Q26: =Q13-$B$8 -> 4633355.7 | V26: 0.06 | W26: =W13/$H$37-1 -> -0.42167114 | X26: =X13/$H$37-1 -> -0.35901899 | Y26: =Y13/$H$37-1 -> -0.27846624 | Z26: =Z13/$H$37-1 -> -0.17106257 | AA26: =AA13/$H$37-1 -> -0.020697429
L27: 0.07 | M27: =M14-$B$8 -> 2223747.6 | N27: =N14-$B$8 -> 2410619 | O27: =O14-$B$8 -> 2639017.4 | P27: =P14-$B$8 -> 2924515.4 | Q27: =Q14-$B$8 -> 3291584.2 | V27: 0.07 | W27: =W14/$H$37-1 -> -0.52999038 | X27: =X14/$H$37-1 -> -0.49049338 | Y27: =Y14/$H$37-1 -> -0.44221927 | Z27: =Z14/$H$37-1 -> -0.38187664 | AA27: =AA14/$H$37-1 -> -0.30429325
K28: WA | L28: 0.08 | M28: =M15-$B$8 -> 1869051.4 | N28: =N15-$B$8 -> 1996006.7 | O28: =O15-$B$8 -> 2146044.9 | P28: =P15-$B$8 -> 2326090.6 | Q28: =Q15-$B$8 -> 2546146.6 | U28: WA | V28: 0.08 | W28: =W15/$H$37-1 -> -0.60495871 | X28: =X15/$H$37-1 -> -0.57812553 | Y28: =Y15/$H$37-1 -> -0.54641358 | Z28: =Z15/$H$37-1 -> -0.50835924 | AA28: =AA15/$H$37-1 -> -0.46184838
A29: ENTERPRISE VALUE | F29: EQUITY VALUE PER SHARE | K29: CC | L29: 0.09 | M29: =M16-$B$8 -> 1609026.5 | N29: =N16-$B$8 -> 1699922.7 | O29: =O16-$B$8 -> 1804802.8 | P29: =P16-$B$8 -> 1927163 | Q29: =Q16-$B$8 -> 2071770.4 | U29: CC | V29: 0.09 | W29: =W16/$H$37-1 -> -0.65991736 | X29: =X16/$H$37-1 -> -0.64070563 | Y29: =Y16/$H$37-1 -> -0.61853824 | Z29: =Z16/$H$37-1 -> -0.59267629 | AA29: =AA16/$H$37-1 -> -0.56211217
A30: PV of Discrete | B30: =SUM(B12:F12) -> 500000.14 | C30: =B30/$B$32 -> 0.22637062 | F30: Equity Value | H30: =C38 -> 2146044.9 | L30: 0.1 | M30: =M17-$B$8 -> 1410256.3 | N30: =N17-$B$8 -> 1477916.1 | O30: =O17-$B$8 -> 1554597.3 | P30: =P17-$B$8 -> 1642232.9 | Q30: =Q17-$B$8 -> 1743350.9 | V30: 0.1 | W30: =W17/$H$37-1 -> -0.70192929 | X30: =X17/$H$37-1 -> -0.68762876 | Y30: =Y17/$H$37-1 -> -0.67142149 | Z30: =Z17/$H$37-1 -> -0.65289889 | AA30: =AA17/$H$37-1 -> -0.63152667
A31: PV of Teminal | B31: =F14 -> 1708767.7 | C31: =B31/$B$32 -> 0.77362938 | F31: Shares Outstanding | H31: =B6 -> 15004697
A32: Enterprise Value | B32: =SUM(B30:B31) -> 2208767.9 | C32: =B32/$B$32 -> 1 | F32: Intransic Value | G32: (USD/sh) | H32: =H30/H31*1000 -> 143.02487
A35: EQUITY VALUE | F35: PREMIUM (DISCOUNT)
A36: Enterprise Value | C36: =B32 -> 2208767.9 | F36: Intransic Value | G36: (USD/sh) | H36: =H32 -> 143.02487
A37: Less: Net Debt | C37: =-62723 -> -62723 | F37: Current Price | G37: (USD/sh) | H37: =315.32 -> 315.32
A38: Equity Value | C38: =SUM(C36:C37) -> 2146044.9 | F38: Premium(Discount) | H38: =(H36-H37)/H37 -> -0.54641358
